langchain_anthropic/__init__.py
langchain_anthropic/chat_models.py
langchain_anthropic/experimental.py
langchain_anthropic/llms.py
langchain_anthropic/output_parsers.py
langchain_anthropic/py.typed
gigachain_anthropic-0.1.23.dist-info/LICENSE
gigachain_anthropic-0.1.23.dist-info/METADATA
gigachain_anthropic-0.1.23.dist-info/WHEEL
gigachain_anthropic-0.1.23.dist-info/RECORD
